{
  "section": "music",
  "date": "2026-06-27",
  "day_of_year": 178,
  "rotation_offset": 10,
  "_rotation_note": "178 % 24 pool-size = 10; keyword slice starts at index 10 (AI vocal cloning). YouTube channel slice: 178 % 6 = 2, starts at ElevenLabs.",
  "core_keywords": ["AI music", "AI 음악", "generative music"],
  "user_seeds": [],
  "skipped_pool_keywords": [
    {"keyword": "AI music plugin",    "reason": "covered today 06-27 — MusicRadar vibe-coding/ai-prompt-plugins"},
    {"keyword": "music AI licensing", "reason": "covered today 06-27 — Billboard ai-music-deals licensing letter"},
    {"keyword": "AI songwriting",     "reason": "adjacent to Suno songwriting video covered 06-26"},
    {"keyword": "Suno",               "reason": "covered 06-26 in both incubator story and songwriting video"}
  ],
  "working_keywords": [
    {
      "keyword": "AI music",
      "type": "core",
      "expansions": [
        "AI music 2026",
        "artificial intelligence music creation",
        "AI music news June 2026",
        "AI 음악 최신 뉴스"
      ]
    },
    {
      "keyword": "AI 음악",
      "type": "core",
      "expansions": [
        "AI 음악 생성 모델",
        "인공지능 음악 제작 도구",
        "생성형 음악 AI",
        "AI 음악 트렌드 2026"
      ]
    },
    {
      "keyword": "generative music",
      "type": "core",
      "expansions": [
        "generative AI music model",
        "generative music platform 2026",
        "AI generative music composition",
        "procedural music generation AI"
      ]
    },
    {
      "keyword": "AI vocal cloning",
      "type": "pool",
      "pool_index": 10,
      "expansions": [
        "AI voice cloning music 2026",
        "voice synthesis singer replica",
        "AI artist voice model",
        "vocal AI deepfake music"
      ]
    },
    {
      "keyword": "text-to-music",
      "type": "pool",
      "pool_index": 11,
      "expansions": [
        "text-to-music AI model 2026",
        "text prompt music generation",
        "text-to-audio music release",
        "텍스트 음악 생성 AI"
      ]
    },
    {
      "keyword": "neural synthesizer",
      "type": "pool",
      "pool_index": 13,
      "expansions": [
        "neural audio synthesis VST",
        "AI synth plugin release 2026",
        "machine learning synthesizer hardware",
        "neural audio instrument DAW"
      ]
    },
    {
      "keyword": "AI mixing",
      "type": "pool",
      "pool_index": 14,
      "expansions": [
        "AI mix tool plugin 2026",
        "automated mixing software DAW",
        "AI mixing mastering workflow",
        "intelligent mix assistant"
      ]
    },
    {
      "keyword": "AI sample generation",
      "type": "pool",
      "pool_index": 15,
      "expansions": [
        "AI sample pack generator 2026",
        "AI drum loop generation",
        "AI sound design samples",
        "generative audio sample tool"
      ]
    },
    {
      "keyword": "AI song cover",
      "type": "pool",
      "pool_index": 16,
      "expansions": [
        "AI cover song generator 2026",
        "AI voice cover music",
        "AI song remake model",
        "AI 커버 음악"
      ]
    },
    {
      "keyword": "AI DJ",
      "type": "pool",
      "pool_index": 18,
      "expansions": [
        "AI DJ software 2026",
        "AI DJ mix generator automated",
        "AI DJ set transitions",
        "AI 디제이 도구"
      ]
    },
    {
      "keyword": "real-time AI music",
      "type": "pool",
      "pool_index": 19,
      "expansions": [
        "real-time music generation AI 2026",
        "live AI music performance tool",
        "interactive generative audio live",
        "AI music live set"
      ]
    },
    {
      "keyword": "Riffusion",
      "type": "pool",
      "pool_index": 20,
      "expansions": [
        "Riffusion AI music 2026",
        "Riffusion new model update",
        "diffusion model music generation",
        "Riffusion vs Udio Stable Audio"
      ]
    },
    {
      "keyword": "AI in Ableton",
      "type": "pool",
      "pool_index": 21,
      "expansions": [
        "AI in Ableton Live 2026",
        "Ableton AI device plugin",
        "Max for Live AI generative",
        "AI music production Ableton workflow"
      ]
    },
    {
      "keyword": "AI in Logic Pro",
      "type": "pool",
      "pool_index": 22,
      "expansions": [
        "Logic Pro AI features 2026",
        "Logic Pro AI session player update",
        "Apple Logic AI instrument",
        "Logic Pro generative AI composition"
      ]
    },
    {
      "keyword": "AI music video",
      "type": "pool",
      "pool_index": 23,
      "expansions": [
        "AI music video generation 2026",
        "AI generated music video tool",
        "generative video music visual",
        "AI 뮤직비디오 생성"
      ]
    }
  ],
  "search_plan": {
    "total_queries": 28,
    "youtube_channels_today": ["ElevenLabs", "Andrew Huang", "Benn Jordan"],
    "_channel_rotation_note": "178 % 6 = 2 → skip first 2 channels (Suno already covered, Udio shift), start at ElevenLabs, Andrew Huang, Benn Jordan",
    "categories": [
      {
        "label": "Music — Core & Generative Models",
        "allowed_domains": [
          "musictech.com", "musicradar.com", "soundonsound.com", "cdm.link",
          "synthtopia.com", "hypebot.com", "music-ally.com", "midiaresearch.com",
          "waterandmusic.com", "completemusicupdate.com", "theverge.com",
          "engadget.com", "techcrunch.com", "billboard.com"
        ],
        "queries": [
          {
            "id": "q01",
            "query": "generative AI music model release 2026",
            "intent": "Broad sweep for new generative music model launches"
          },
          {
            "id": "q02",
            "query": "text-to-music AI model new 2026 site:musictech.com OR site:cdm.link OR site:synthtopia.com",
            "intent": "Trade-press coverage of text-to-music model launches"
          },
          {
            "id": "q03",
            "query": "AI 음악 생성 모델 2026 site:musictech.com OR site:hypebot.com OR site:music-ally.com",
            "intent": "Korean-market angle on AI music generation"
          },
          {
            "id": "q04",
            "query": "Udio AI music update new feature 2026 site:musictech.com OR site:musicradar.com OR site:hypebot.com",
            "intent": "Udio updates — not covered recently"
          },
          {
            "id": "q05",
            "query": "Stable Audio Stability AI music open weights 2026 site:musictech.com OR site:cdm.link OR site:theverge.com",
            "intent": "Stable Audio model or open-weight release"
          },
          {
            "id": "q06",
            "query": "ElevenLabs music AI generation 2026 site:musictech.com OR site:techcrunch.com OR site:engadget.com",
            "intent": "ElevenLabs music features"
          },
          {
            "id": "q07",
            "query": "Google Lyria MusicLM AI music model 2026 site:musictech.com OR site:synthtopia.com OR site:theverge.com",
            "intent": "Google DeepMind music model updates"
          },
          {
            "id": "q08",
            "query": "Riffusion AI music generation update 2026 site:musictech.com OR site:cdm.link OR site:synthtopia.com",
            "intent": "Riffusion model or platform news"
          }
        ]
      },
      {
        "label": "Music — Vocal AI & Song Covers",
        "allowed_domains": [
          "musictech.com", "musicradar.com", "soundonsound.com", "cdm.link",
          "hypebot.com", "music-ally.com", "midiaresearch.com", "billboard.com",
          "pitchfork.com", "rollingstone.com", "theverge.com", "engadget.com",
          "techcrunch.com", "completemusicupdate.com"
        ],
        "queries": [
          {
            "id": "q09",
            "query": "AI vocal cloning music artist voice 2026 site:musictech.com OR site:soundonsound.com OR site:cdm.link",
            "intent": "New AI vocal cloning tools for music production"
          },
          {
            "id": "q10",
            "query": "AI voice synthesis singer model release 2026 site:hypebot.com OR site:music-ally.com OR site:billboard.com",
            "intent": "Industry and rights angle on AI singing voice"
          },
          {
            "id": "q11",
            "query": "AI song cover generator voice model 2026 site:musictech.com OR site:musicradar.com OR site:pitchfork.com",
            "intent": "AI cover song tools and notable releases"
          },
          {
            "id": "q12",
            "query": "AI 커버곡 목소리 복제 2026 site:hypebot.com OR site:music-ally.com",
            "intent": "Korean-language angle on AI vocal covers"
          }
        ]
      },
      {
        "label": "Music — Producer Tools, DAW & Workflow",
        "allowed_domains": [
          "musictech.com", "musicradar.com", "soundonsound.com", "cdm.link",
          "attackmagazine.com", "synthtopia.com", "bedroomproducersblog.com",
          "gearnews.com", "djmag.com", "mixmag.net", "hypebot.com",
          "music-ally.com", "theverge.com", "engadget.com"
        ],
        "queries": [
          {
            "id": "q13",
            "query": "AI mixing tool automated plugin DAW 2026 site:musictech.com OR site:musicradar.com OR site:soundonsound.com",
            "intent": "AI mixing plugin and automated mix tool releases"
          },
          {
            "id": "q14",
            "query": "AI mastering tool plugin 2026 LANDR iZotope Ozone site:musictech.com OR site:bedroomproducersblog.com OR site:gearnews.com",
            "intent": "AI mastering service and plugin updates"
          },
          {
            "id": "q15",
            "query": "AI stem separation source separation tool 2026 site:musictech.com OR site:cdm.link OR site:synthtopia.com",
            "intent": "AI stem splitting tool updates"
          },
          {
            "id": "q16",
            "query": "AI sample generation pack sound design 2026 site:musictech.com OR site:bedroomproducersblog.com OR site:attackmagazine.com",
            "intent": "AI-generated sample pack tools"
          },
          {
            "id": "q17",
            "query": "neural synthesizer AI synth plugin VST 2026 site:musictech.com OR site:cdm.link OR site:gearnews.com",
            "intent": "Neural synth and AI instrument plugin launches"
          },
          {
            "id": "q18",
            "query": "AI in Ableton Live plugin Max for Live 2026 site:musictech.com OR site:cdm.link OR site:bedroomproducersblog.com",
            "intent": "AI integrations in Ableton Live"
          },
          {
            "id": "q19",
            "query": "Logic Pro AI features session player update 2026 site:musictech.com OR site:musicradar.com OR site:synthtopia.com",
            "intent": "Apple Logic Pro AI feature updates"
          }
        ]
      },
      {
        "label": "Music — DJ, Electronic & Real-Time",
        "allowed_domains": [
          "djmag.com", "mixmag.net", "residentadvisor.net", "factmag.com",
          "attackmagazine.com", "cdm.link", "musictech.com", "theverge.com",
          "engadget.com"
        ],
        "queries": [
          {
            "id": "q20",
            "query": "AI DJ software automated mixing set 2026 site:djmag.com OR site:mixmag.net OR site:residentadvisor.net",
            "intent": "AI DJ tools and auto-mixing coverage"
          },
          {
            "id": "q21",
            "query": "real-time AI music generation live performance 2026 site:cdm.link OR site:attackmagazine.com OR site:musictech.com",
            "intent": "Real-time and live AI music tools"
          },
          {
            "id": "q22",
            "query": "interactive generative AI audio live set tool 2026 site:factmag.com OR site:residentadvisor.net OR site:cdm.link",
            "intent": "Electronic music producers using generative AI live"
          }
        ]
      },
      {
        "label": "Music — Music Video & Visual AI",
        "allowed_domains": [
          "musictech.com", "pitchfork.com", "rollingstone.com", "billboard.com",
          "theverge.com", "engadget.com", "techcrunch.com", "cdm.link"
        ],
        "queries": [
          {
            "id": "q23",
            "query": "AI generated music video 2026 artist release site:pitchfork.com OR site:rollingstone.com OR site:billboard.com",
            "intent": "Notable AI music video releases by artists"
          },
          {
            "id": "q24",
            "query": "AI music video tool generator visual 2026 site:musictech.com OR site:theverge.com OR site:cdm.link",
            "intent": "AI music video generation tools"
          },
          {
            "id": "q25",
            "query": "AI 뮤직비디오 생성 도구 2026",
            "intent": "Korean-language coverage of AI music video tools"
          }
        ]
      },
      {
        "label": "Music — Social (YouTube & Instagram)",
        "allowed_domains": ["youtube.com", "youtu.be", "instagram.com"],
        "queries": [
          {
            "id": "q26",
            "query": "site:youtube.com ElevenLabs music AI 2026",
            "intent": "ElevenLabs channel — AI music tool demos (rotated in today)"
          },
          {
            "id": "q27",
            "query": "site:youtube.com \"Andrew Huang\" AI music production 2026",
            "intent": "Andrew Huang channel — AI music experiments (rotated in today)"
          },
          {
            "id": "q28",
            "query": "site:youtube.com \"Benn Jordan\" AI generative music 2026",
            "intent": "Benn Jordan channel — AI music analysis/commentary (rotated in today)"
          }
        ]
      }
    ]
  }
}
