{
  "date": "2026-07-01",
  "selection_mode": "user",
  "picks": [
    {
      "category": "render",
      "tool": "Polygonflow",
      "accent": "#f5a623",
      "motif": "cube",
      "source": "CG Channel",
      "published_iso": "2026-06-30T00:00:00Z",
      "og_image": "https://www.cgchannel.com/wp-content/uploads/2026/05/260630_Dash112_Stacking.mp4",
      "url": "https://www.cgchannel.com/2026/06/check-out-the-new-features-in-ue5-world-building-tool-dash/",
      "excerpt": "Polygonflow has released Dash 1.12 for Unreal Engine 5, adding scene-layout tools - Place in Grid, Place in Circle, and Vertical Stacking - plus scattering-toolset updates for faster world-building."
    },
    {
      "category": "figma",
      "tool": "AI Slop",
      "accent": "#ff2d55",
      "motif": "frame",
      "source": "Creative Bloq",
      "published_iso": "2026-06-29T14:28:18Z",
      "og_image": "https://cdn.mos.cms.futurecdn.net/vMFFimyrwGXSaxBhw8dLz5-2560-80.jpg",
      "url": "https://www.creativebloq.com/ai/ai-slop-has-become-a-harmful-insult-hurled-around-with-no-evidence-game-developers-claim",
      "excerpt": "Game developers argue that 'AI slop' has become a harmful insult applied indiscriminately and without evidence, reflecting deepening tension over AI's role in creative work."
    },
    {
      "category": "figma",
      "tool": "Builder.io",
      "accent": "#7928ca",
      "motif": "sphere",
      "source": "Builder.io",
      "published_iso": "2026-06-29T18:00:00Z",
      "og_image": "https://cdn.builder.io/api/v1/image/assets/YJIGb4i01jvw0SRdL5Bt/271665f687c94f8ea020739bd0507825?format=webp&width=800",
      "url": "https://www.builder.io/blog/building-without-the-handoffs",
      "excerpt": "Builder.io argues AI is changing who can build software: the fastest teams run agents inside their real systems, removing design-to-engineering handoff bottlenecks."
    },
    {
      "category": "vr",
      "tool": "Meta",
      "accent": "#2ec5c5",
      "motif": "frame",
      "source": "Road to VR",
      "published_iso": "2026-06-30T12:22:19Z",
      "og_image": "https://roadtovr.com/wp-content/uploads/2026/06/Meta-Brain2QWERTY.jpeg",
      "url": "https://roadtovr.com/meta-brain-ai-telepathy-improved-bci/",
      "excerpt": "Meta researchers report improved thought-to-text decoding, moving their brain-computer interface a step closer to silent, hands-free text input for spatial computing."
    }
  ]
}